README.md
setup.cfg
setup.py
vk_addon/__init__.py
vk_addon/get_random_id.py
vk_addon/vk_addon.py
vk_addon.egg-info/PKG-INFO
vk_addon.egg-info/SOURCES.txt
vk_addon.egg-info/dependency_links.txt
vk_addon.egg-info/not-zip-safe
vk_addon.egg-info/top_level.txt