Metadata-Version: 1.0
Name: vk-addon
Version: 1.3.2
Summary: VkAddon - помощник vk_api.
Home-page: UNKNOWN
Author: UNKNOWN
Author-email: play.fanner@gmail.com
License: UNKNOWN
Platform: UNKNOWN
